LICENSE.txt
MANIFEST.in
README.rst
setup.py
dominos/__init__.py
dominos/api.py
dominos/version.py
dominos.egg-info/PKG-INFO
dominos.egg-info/SOURCES.txt
dominos.egg-info/dependency_links.txt
dominos.egg-info/not-zip-safe
dominos.egg-info/requires.txt
dominos.egg-info/top_level.txt