Metadata-Version: 1.1
Name: dominos
Version: 0.0.3
Summary: Dominos Pizza API
Home-page: https://github.com/tomasbasham/dominos
Author: Tomas Basham
Author-email: me@tomasbasham.co.uk
License: MIT
Keywords: dominos pizza api
Platform: UNKNOWN
Classifier: Development Status :: 3 - Alpha
Classifier: Intended Audience :: Developers
Classifier: License :: OSI Approved :: MIT License
Classifier: Natural Language :: English
Classifier: Programming Language :: Python
Classifier: Topic :: Software Development
